setup.cfg
setup.py
fonetipy/__init__.py
fonetipy/fonetipy.py
fonetipy/fonetipy_test.py
fonetipy.egg-info/PKG-INFO
fonetipy.egg-info/SOURCES.txt
fonetipy.egg-info/dependency_links.txt
fonetipy.egg-info/requires.txt
fonetipy.egg-info/top_level.txt