Metadata-Version: 1.0
Name: fonetipy
Version: 0.1.1
Summary: BuscarBr Python Algorithm
Home-page: https://github.com/arthur-alves/fonetipy
Author: Arthur Alves
Author-email: arthur.4lves@gmail.com
License: MIT License
Keywords: buscabr fonetipy fonetico
Platform: UNKNOWN
